LICENSE
MANIFEST.in
README.rst
setup.py
talon/__init__.py
talon/constants.py
talon/html_quotations.py
talon/quotations.py
talon/utils.py
talon/signature/__init__.py
talon/signature/bruteforce.py
talon/signature/constants.py
talon/signature/extraction.py
talon/signature/data/__init__.py
talon/signature/data/classifier
talon/signature/data/classifier_01.npy
talon/signature/data/classifier_02.npy
talon/signature/data/classifier_03.npy
talon/signature/data/classifier_04.npy
talon/signature/data/classifier_05.npy
talon/signature/data/train.data
talon/signature/learning/__init__.py
talon/signature/learning/classifier.py
talon/signature/learning/dataset.py
talon/signature/learning/featurespace.py
talon/signature/learning/helpers.py
talon_v3.egg-info/PKG-INFO
talon_v3.egg-info/SOURCES.txt
talon_v3.egg-info/dependency_links.txt
talon_v3.egg-info/requires.txt
talon_v3.egg-info/top_level.txt
talon_v3.egg-info/zip-safe