Metadata-Version: 2.1
Name: talon-v3
Version: 1.0.1
Summary: Mailgun library to extract message quotations and signatures.
Home-page: https://github.com/mailgun/talon
Author: Mailgun Inc.
Author-email: admin@mailgunhq.com
License: APACHE2
License-File: LICENSE
Requires-Dist: lxml
Requires-Dist: regex
Requires-Dist: numpy
Requires-Dist: scipy
Requires-Dist: scikit-learn>=1.0.0
Requires-Dist: chardet
Requires-Dist: faust-cchardet
Requires-Dist: cssselect
Requires-Dist: six
Requires-Dist: html5lib
Requires-Dist: joblib
